robotframework_reportlens/__init__.py
robotframework_reportlens/__main__.py
robotframework_reportlens/builder.py
robotframework_reportlens/cli.py
robotframework_reportlens/generator.py
robotframework_reportlens/model.py
robotframework_reportlens/serialize.py
robotframework_reportlens/template/template.html
robotframework_reportlens-0.1.3.dist-info/licenses/LICENSE
robotframework_reportlens-0.1.3.dist-info/METADATA
robotframework_reportlens-0.1.3.dist-info/WHEEL
robotframework_reportlens-0.1.3.dist-info/entry_points.txt
robotframework_reportlens-0.1.3.dist-info/top_level.txt
robotframework_reportlens-0.1.3.dist-info/RECORD
