Metadata-Version: 2.4
Name: robotframework-reportlens
Version: 0.1.3
Summary: Generate a modern, interactive HTML report from Robot Framework output.xml
Author-email: Deekshith Poojary <deekshithpoojary355@gmail.com>
License-Expression: Apache-2.0
Project-URL: Repository, https://github.com/deekshith-poojary98/robotframework-reportlens
Keywords: robotframework,report,html,testing,cli,log
Classifier: Development Status :: 4 - Beta
Classifier: Intended Audience :: Developers
Classifier: Programming Language :: Python :: 3.8
Classifier: Programming Language :: Python :: 3.9
Classifier: Programming Language :: Python :: 3.10
Classifier: Programming Language :: Python :: 3.11
Classifier: Programming Language :: Python :: 3.12
Classifier: Programming Language :: Python :: 3.13
Classifier: Programming Language :: Python :: 3.14
Classifier: Topic :: Software Development :: Libraries :: Python Modules
Classifier: Framework :: Robot Framework
Requires-Python: >=3.8
License-File: LICENSE
Requires-Dist: robotframework>=6.0
Provides-Extra: dev
Requires-Dist: pytest>=7.0; extra == "dev"
Requires-Dist: pytest-cov; extra == "dev"
Requires-Dist: ruff; extra == "dev"
Requires-Dist: build; extra == "dev"
Dynamic: license-file
